camel/__init__.py
camel/__pycache__/__init__.cpython-35.pyc
camel/tests/__init__.py
camel/tests/test_docs.py
camel/tests/test_general.py
camel/tests/__pycache__/__init__.cpython-35.pyc
camel/tests/__pycache__/test_docs.cpython-35-PYTEST.pyc
camel/tests/__pycache__/test_general.cpython-35-PYTEST.pyc
camel-0.1.2.dist-info/DESCRIPTION.rst
camel-0.1.2.dist-info/METADATA
camel-0.1.2.dist-info/RECORD
camel-0.1.2.dist-info/WHEEL
camel-0.1.2.dist-info/metadata.json
camel-0.1.2.dist-info/top_level.txt
